MANIFEST.in
README.rst
flake8_pep257.py
requirements.txt
setup.py
flake8_pep257.egg-info/PKG-INFO
flake8_pep257.egg-info/SOURCES.txt
flake8_pep257.egg-info/dependency_links.txt
flake8_pep257.egg-info/entry_points.txt
flake8_pep257.egg-info/requires.txt
flake8_pep257.egg-info/top_level.txt
flake8_pep257.egg-info/zip-safe