Metadata-Version: 1.1
Name: flake8-pep257
Version: 1.0.2
Summary: Flake8 plugin for the pep257 Python utility.
Home-page: https://github.com/Robpol86/flake8-pep257
Author: @Robpol86
Author-email: robpol86@gmail.com
License: MIT
Keywords: flake8 pep257 docstrings
Platform: UNKNOWN
Classifier: Development Status :: 5 - Production/Stable
Classifier: Environment :: MacOS X
Classifier: Environment :: Win32 (MS Windows)
Classifier: Intended Audience :: Developers
Classifier: License :: OSI Approved :: MIT License
Classifier: Operating System :: MacOS :: MacOS X
Classifier: Operating System :: Microsoft :: Windows
Classifier: Operating System :: POSIX
Classifier: Operating System :: POSIX :: Linux
Classifier: Programming Language :: Python :: 2.6
Classifier: Programming Language :: Python :: 2.7
Classifier: Programming Language :: Python :: 3.3
Classifier: Programming Language :: Python :: 3.4
Classifier: Programming Language :: Python :: Implementation :: PyPy
Classifier: Topic :: Software Development :: Quality Assurance
Requires: flake8
Requires: pep257
